cloudbrain/__init__.py
cloudbrain/run.py
cloudbrain/version.py
cloudbrain/connectors/__init__.py
cloudbrain/connectors/muse.py
cloudbrain/connectors/museio.py
cloudbrain/connectors/neurosky.py
cloudbrain/connectors/openbci.py
cloudbrain/connectors/thinkgear.py
cloudbrain/core/__init__.py
cloudbrain/core/auth.py
cloudbrain/core/config.dev.json
cloudbrain/core/config.json
cloudbrain/core/config.py
cloudbrain/core/model.py
cloudbrain/core/signal.py
cloudbrain/modules/__init__.py
cloudbrain/modules/interface.py
cloudbrain/modules/runner.py
cloudbrain/modules/filters/__init__.py
cloudbrain/modules/filters/band.py
cloudbrain/modules/filters/threshold.py
cloudbrain/modules/sinks/__init__.py
cloudbrain/modules/sinks/csvout.py
cloudbrain/modules/sinks/plotly_stream.py
cloudbrain/modules/sinks/pyplot.py
cloudbrain/modules/sinks/stdout.py
cloudbrain/modules/sources/__init__.py
cloudbrain/modules/sources/beat.py
cloudbrain/modules/sources/mock.py
cloudbrain/modules/sources/muse.py
cloudbrain/modules/sources/neurosky.py
cloudbrain/modules/sources/openbci.py
cloudbrain/modules/transforms/__init__.py
cloudbrain/modules/transforms/bpm.py
cloudbrain/modules/transforms/fft.py
cloudbrain/modules/transforms/peak.py
cloudbrain/publishers/__init__.py
cloudbrain/publishers/interface.py
cloudbrain/publishers/pipe.py
cloudbrain/publishers/rabbitmq.py
cloudbrain/schema/__init__.py
cloudbrain/schema/module_configs.json
cloudbrain/schema/supported_devices.json
cloudbrain/subscribers/__init__.py
cloudbrain/subscribers/interface.py
cloudbrain/subscribers/rabbitmq.py
cloudbrain-0.0.18.dist-info/DESCRIPTION.rst
cloudbrain-0.0.18.dist-info/METADATA
cloudbrain-0.0.18.dist-info/RECORD
cloudbrain-0.0.18.dist-info/WHEEL
cloudbrain-0.0.18.dist-info/entry_points.txt
cloudbrain-0.0.18.dist-info/metadata.json
cloudbrain-0.0.18.dist-info/top_level.txt
