Metadata-Version: 2.0
Name: cloudbrain
Version: 0.0.18
Summary: Platform for wearable data analysis.
Home-page: https://github.com/cloudbrain/cloudbrain
Author: Marion Le Borgne
Author-email: marion@ebrain.io
License: UNKNOWN
Download-URL: https://github.com/cloudbrain/cloudbrain/archive/0.0.18.tar.gz
Platform: UNKNOWN
Requires-Dist: pika (==0.10)
Requires-Dist: pyserial (==2.7)
Requires-Dist: requests[security] (==2.18.1)
Requires-Dist: simplejson (==3.8.2)
Provides-Extra: analytics
Requires-Dist: mne (==0.10.0); extra == 'analytics'
Requires-Dist: numpy (==1.11.2); extra == 'analytics'
Requires-Dist: scipy (==0.18.1); extra == 'analytics'
Provides-Extra: muse
Requires-Dist: python-osc (==1.6); python_version>="3" and extra == 'muse'
